tybsc2/__init__.py
tybsc2-0.0.1.dist-info/METADATA
tybsc2-0.0.1.dist-info/WHEEL
tybsc2-0.0.1.dist-info/top_level.txt
tybsc2-0.0.1.dist-info/RECORD
