Metadata-Version: 2.4
Name: tybsc2
Version: 0.0.1
Summary: TYBSc OS Practical Codes (CPU Scheduling, Paging, Memory Mgmt)
Author: Bipin Yadav
Requires-Python: >=3.6
Dynamic: author
Dynamic: description-content-type
Dynamic: requires-python
Dynamic: summary
